autobean/__init__.py
autobean/include/README.md
autobean/include/__init__.py
autobean/include/plugin.py
autobean/narration/README.md
autobean/narration/__init__.py
autobean/narration/comments.py
autobean/narration/plugin.py
autobean/refactor/README.md
autobean/share/README.md
autobean/share/__init__.py
autobean/share/docs/advanced.md
autobean/share/docs/rationale.md
autobean/share/include.py
autobean/share/include_context.py
autobean/share/link_accounts.py
autobean/share/plugin.py
autobean/share/policy_lib.py
autobean/share/policy_lib_test.py
autobean/share/split_account.py
autobean/share/viewpoint_lib.py
autobean/sorted/README.md
autobean/sorted/__init__.py
autobean/sorted/plugin.py
autobean/stock_split/README.md
autobean/stock_split/__init__.py
autobean/stock_split/plugin.py
autobean/stock_split/plugin_test.py
autobean/truelayer/README.md
autobean/truelayer/__init__.py
autobean/truelayer/importer.py
autobean/utils/__init__.py
autobean/utils/compare.py
autobean/utils/deduplicate.py
autobean/utils/error_lib.py
autobean/utils/plugin_lib.py
autobean/utils/plugin_test_utils.py
autobean/xcheck/README.md
autobean/xcheck/__init__.py
autobean/xcheck/plugin.py
autobean-0.2.2.dist-info/WHEEL
autobean-0.2.2.dist-info/METADATA
autobean-0.2.2.dist-info/licenses/LICENSE
autobean-0.2.2.dist-info/RECORD
