Metadata-Version: 2.1
Name: autobean
Version: 0.2.2
Summary: A collection of plugins and scripts that help automating bookkeeping with beancount
License: GPL2
Author-email: SEIAROTg <seiarotg@gmail.com>
Requires-Python: >=3.10
Requires-Dist: beancount>=2.3.5
Requires-Dist: python-dateutil>=2.8.2
Requires-Dist: pyyaml>=6.0.1
Requires-Dist: requests>=2.31.0
